README.rst
setup.py
django_news/__init__.py
django_news/admin.py
django_news/apps.py
django_news/models.py
django_news/urls.py
django_news/views.py
django_news/locale/ru/LC_MESSAGES/django.po
django_news/migrations/0001_initial.py
django_news/migrations/0002_auto_20160811_1411.py
django_news/migrations/__init__.py
django_news/templatetags/__init__.py
django_news/templatetags/django_news.py
django_news/tests/__init__.py
django_news/tests/runtests.py
django_news/tests/test_models.py
django_news/tests/test_templatetags.py
django_news/tests/urls.py
django_simple_news_app.egg-info/PKG-INFO
django_simple_news_app.egg-info/SOURCES.txt
django_simple_news_app.egg-info/SOURCES.txt.py
django_simple_news_app.egg-info/dependency_links.txt
django_simple_news_app.egg-info/dependency_links.txt.py
django_simple_news_app.egg-info/not-zip-safe
django_simple_news_app.egg-info/requires.txt
django_simple_news_app.egg-info/requires.txt.py
django_simple_news_app.egg-info/top_level.txt
django_simple_news_app.egg-info/top_level.txt.py